MANIFEST.in
setup.cfg
setup.py
restfulie/__init__.py
restfulie/converters.py
restfulie/dsl.py
restfulie/links.py
restfulie/opensearch.py
restfulie/parser.py
restfulie/processor.py
restfulie/request.py
restfulie/response.py
restfulie/restfulie.py
restfulie.egg-info/PKG-INFO
restfulie.egg-info/SOURCES.txt
restfulie.egg-info/dependency_links.txt
restfulie.egg-info/requires.txt
restfulie.egg-info/top_level.txt
restfulie/resources/__init__.py
restfulie/resources/json.py
restfulie/resources/xml.py