Metadata-Version: 1.0
Name: restfulie
Version: 0.9.2
Summary: Writing hypermedia aware resource based clients and servers
Home-page: http://restfulie.caelumobjects.com/
Author:  
Author-email:  
License: UNKNOWN
Download-URL: https://github.com/caelum/restfulie-py
Keywords: restfulie rest http hypermedia
Platform: UNKNOWN
Classifier: Development Status :: 4 - Beta
Classifier: Environment :: Web Environment
Classifier: Intended Audience :: Developers
Classifier: License :: OSI Approved :: Apache Software License
Classifier: Operating System :: MacOS :: MacOS X
Classifier: Operating System :: Microsoft :: Windows
Classifier: Operating System :: POSIX
Classifier: Programming Language :: Python
